README.rst
setup.py
repl/__init__.py
repl/cli.py
repl/repl.py
repl/util.py
repl.egg-info/PKG-INFO
repl.egg-info/SOURCES.txt
repl.egg-info/dependency_links.txt
repl.egg-info/entry_points.txt
repl.egg-info/requires.txt
repl.egg-info/top_level.txt