Metadata-Version: 1.1
Name: repl
Version: 1.0
Summary: Run command as REPL-environment (useful for git!).
Home-page: https://github.com/mbr/repl
Author: Marc Brinkmann
Author-email: git@marcbrinkmann.de
License: MIT
Platform: UNKNOWN
Classifier: Programming Language :: Python :: 2
Classifier: Programming Language :: Python :: 3
